openai_wrapper/__init__.py
openai_wrapper/openai_wrapper.py
openai_chat_api_wrapper-0.1.1.dist-info/METADATA
openai_chat_api_wrapper-0.1.1.dist-info/WHEEL
openai_chat_api_wrapper-0.1.1.dist-info/top_level.txt
openai_chat_api_wrapper-0.1.1.dist-info/RECORD
